Metadata-Version: 2.1
Name: django-boot-siba
Version: 1.0.0
Summary: Django Translation Files in json format
Home-page: https://github.com/django-boot/siba
Author: Django Boot
Author-email: djangoboot@proton.me
Classifier: Environment :: Web Environment
Classifier: Framework :: Django
Classifier: Framework :: Django :: 4.2
Classifier: Intended Audience :: Developers
Classifier: Operating System :: OS Independent
Classifier: Programming Language :: Python
Classifier: Programming Language :: Python :: 3 :: Only
Classifier: Programming Language :: Python :: 3.9
Classifier: Topic :: Internet :: WWW/HTTP
Requires-Python: >=3.9
License-File: LICENSE
Requires-Dist: Django>=4.2
